baconian/__init__.py
baconian/version.py
baconian/algo/__init__.py
baconian/algo/algo.py
baconian/algo/ddpg.py
baconian/algo/dqn.py
baconian/algo/dyna.py
baconian/algo/gps.py
baconian/algo/mbmf.py
baconian/algo/model_ensemble.py
baconian/algo/mpc.py
baconian/algo/ppo.py
baconian/algo/rl_algo.py
baconian/algo/utils.py
baconian/algo/distribution/__init__.py
baconian/algo/distribution/mvn.py
baconian/algo/dynamics/__init__.py
baconian/algo/dynamics/dynamics_model.py
baconian/algo/dynamics/gaussian_mixture_dynamics_prior.py
baconian/algo/dynamics/gaussian_process_dynamiocs_model.py
baconian/algo/dynamics/linear_dynamics_model.py
baconian/algo/dynamics/mlp_dynamics_model.py
baconian/algo/dynamics/random_dynamics_model.py
baconian/algo/dynamics/reward_func/__init__.py
baconian/algo/dynamics/reward_func/reward_func.py
baconian/algo/dynamics/terminal_func/__init__.py
baconian/algo/dynamics/terminal_func/terminal_func.py
baconian/algo/dynamics/third_party/__init__.py
baconian/algo/dynamics/third_party/gmm.py
baconian/algo/dynamics/third_party/mgpr.py
baconian/algo/misc/__init__.py
baconian/algo/misc/epsilon_greedy.py
baconian/algo/misc/placeholder_input.py
baconian/algo/misc/replay_buffer.py
baconian/algo/misc/sample_processor.py
baconian/algo/policy/__init__.py
baconian/algo/policy/constant_action_policy.py
baconian/algo/policy/deterministic_mlp.py
baconian/algo/policy/ilqr_policy.py
baconian/algo/policy/lqr_policy.py
baconian/algo/policy/normal_distribution_mlp.py
baconian/algo/policy/policy.py
baconian/algo/policy/random_policy.py
baconian/algo/value_func/__init__.py
baconian/algo/value_func/mlp_q_value.py
baconian/algo/value_func/mlp_v_value.py
baconian/algo/value_func/value_func.py
baconian/benchmark/__init__.py
baconian/benchmark/get_result.py
baconian/benchmark/run_benchmark.py
baconian/benchmark/visualisation.py
baconian/benchmark/ddpg_benchmark/__init__.py
baconian/benchmark/ddpg_benchmark/average_calculator.py
baconian/benchmark/ddpg_benchmark/batchCheetah.sh
baconian-0.2.6.dist-info/LICENSE
baconian-0.2.6.dist-info/METADATA
baconian-0.2.6.dist-info/WHEEL
baconian-0.2.6.dist-info/top_level.txt
baconian-0.2.6.dist-info/RECORD
