Metadata-Version: 2.1
Name: baconian
Version: 0.2.6
Summary: model-based reinforcement learning toolbox
Home-page: https://github.com/cap-ntu/baconian-project
Author: Linsen Dong
Author-email: linsen001@e.ntu.edu.sg
License: MIT License
Platform: UNKNOWN
Requires-Python: >=3.5
Requires-Dist: pip (>=20.0)
Requires-Dist: pybullet (>=2.7.4)
Requires-Dist: absl-py (>=0.7.0)
Requires-Dist: astor (>=0.7.1)
Requires-Dist: cffi (>=1.12.2)
Requires-Dist: chardet (>=3.0.4)
Requires-Dist: Cython (>=0.29.6)
Requires-Dist: future (>=0.17.1)
Requires-Dist: gast (>=0.2.2)
Requires-Dist: glfw (>=1.7.1)
Requires-Dist: GPUtil (>=1.4.0)
Requires-Dist: grpcio (>=1.19.0)
Requires-Dist: gym (==0.12.0)
Requires-Dist: h5py (>=2.9.0)
Requires-Dist: json-tricks (>=3.13.0)
Requires-Dist: lockfile (>=0.12.2)
Requires-Dist: Markdown (>=3.0.1)
Requires-Dist: numpy (>=1.16.2)
Requires-Dist: overrides (>=1.9)
Requires-Dist: pbr (>=5.1.3)
Requires-Dist: Pillow (>=5.4.1)
Requires-Dist: pycparser (>=2.19)
Requires-Dist: pyglet (>=1.3.2)
Requires-Dist: PyOpenGL (>=3.1.0)
Requires-Dist: requests (>=2.21.0)
Requires-Dist: scipy (>=1.2.1)
Requires-Dist: six (>=1.12.0)
Requires-Dist: setuptools (>=41.0.0)
Requires-Dist: tensorflow-probability (==0.7.0)
Requires-Dist: transitions (>=0.6.9)
Requires-Dist: typeguard (>=2.1.0)
Requires-Dist: urllib3 (>=1.24.2)
Requires-Dist: Werkzeug (>=0.15.3)
Requires-Dist: coverage (>=4.5.2)
Requires-Dist: codecov (>=2.0.15)
Requires-Dist: pandas (>=0.24.2)
Requires-Dist: autograd (>=1.2)
Requires-Dist: gpflow (==1.4.1)
Requires-Dist: matplotlib (>=3.0.3)
Requires-Dist: seaborn (>=0.9.0)
Requires-Dist: roboschool (==1.0.48)
Requires-Dist: opencv-python (>=4.1.0.25)
Requires-Dist: scikit-learn (>=0.21.1)
Requires-Dist: atari-py (>=0.1.14)
